{
  "type": "apoli:action_on_hit",
  "bientity_action": {
    "type": "apoli:and",
    "actions": [
      {
        "type": "apoli:target_action",
        "action": {
          "type": "apoli:apply_effect",
          "effect": {
            "effect": "minecraft:poison",
            "duration": 200,
            "amplifier": 0
          }
        }
      }
    ]
  },
  "bientity_condition": {
    "type": "apoli:actor_condition",
    "condition": {
      "type": "apoli:or",
      "conditions": [
        {
          "type": "apoli:inventory",
          "process_mode": "items",
          "item_condition": {
            "type": "shape-shifter-curse:is_weapon"
          },
          "slots": [
            "weapon.mainhand"
          ],
          "inverted": true
        },
        {
          "type": "apoli:inventory",
          "process_mode": "items",
          "comparison": "==",
          "compare_to": 0,
          "slots": [
            "weapon.mainhand"
          ]
        }
      ]
    }
  }
}